pyharsh/__init__.py
pyharsh/hello.py
pyharsh-0.0.1.dist-info/METADATA
pyharsh-0.0.1.dist-info/WHEEL
pyharsh-0.0.1.dist-info/top_level.txt
pyharsh-0.0.1.dist-info/RECORD
